dialog_workflow/Act.py
dialog_workflow/Constants.py
dialog_workflow/DialogWorkflow.py
dialog_workflow/TablesAsObjects.py
dialog_workflow/__init__.py
dialog_workflow/test.py
dialog_workflow/utils.py
dialog_workflow_local_python_package-0.0.21.dist-info/METADATA
dialog_workflow_local_python_package-0.0.21.dist-info/WHEEL
dialog_workflow_local_python_package-0.0.21.dist-info/top_level.txt
dialog_workflow_local_python_package-0.0.21.dist-info/RECORD
