Metadata-Version: 2.1
Name: dialog-workflow-local-python-package
Version: 0.0.21
Summary: PyPI Package for dialog workflow
Home-page: https://github.com/javatechy/dokr
Author: Circles
Author-email: info@circle.life
Classifier: Programming Language :: Python :: 3
Classifier: License :: Other/Proprietary License
Classifier: Operating System :: OS Independent
